deepair_encoder/__init__.py
deepair_encoder/encoder.py
deepair_encoder/utils/__init__.py
deepair_encoder/utils/encoder_tools.py
deepair_encoder/utils/logger.py
deepair_encoder/utils/splitters.py
deepair_encoder-0.0.9.dist-info/LICENSE
deepair_encoder-0.0.9.dist-info/METADATA
deepair_encoder-0.0.9.dist-info/WHEEL
deepair_encoder-0.0.9.dist-info/top_level.txt
deepair_encoder-0.0.9.dist-info/RECORD
