Metadata-Version: 2.1
Name: deepair-encoder
Version: 0.0.9
Summary: This is a sub modular package for encoding
Home-page: https://bitbucket.org/deepair/
Author: DeepAir Dev
Author-email: naman@deepair.io
License: UNKNOWN
Platform: UNKNOWN
Classifier: Intended Audience :: Developers
Classifier: Programming Language :: Python :: 3
Classifier: License :: OSI Approved :: MIT License
Classifier: Operating System :: OS Independent
